iscard/__init__.py
iscard/__main__.py
iscard/core.py
iscard/model.py
iscard-0.0.5.dist-info/LICENSE
iscard-0.0.5.dist-info/METADATA
iscard-0.0.5.dist-info/WHEEL
iscard-0.0.5.dist-info/entry_points.txt
iscard-0.0.5.dist-info/top_level.txt
iscard-0.0.5.dist-info/RECORD
